MixacLib/__init__.py
MixacLib/cons.py
MixacLib/system.py
MixacLib/mc/__init__.py
MixacLib/mc/anticheat.py
MixacLib-2.2.0.dist-info/LICENSE
MixacLib-2.2.0.dist-info/METADATA
MixacLib-2.2.0.dist-info/WHEEL
MixacLib-2.2.0.dist-info/top_level.txt
MixacLib-2.2.0.dist-info/RECORD
