Metadata-Version: 2.1
Name: MixacLib
Version: 2.2.0
Summary: MixacLib
Home-page: https://gitee.com/tumuidle/MixacLib
Author: tumuidle
Author-email: mixacprod@idlestudios.top
License: UNKNOWN
Project-URL: Issues, https://gitee.com/tumuidle/MixacLib/issues
Platform: UNKNOWN
Classifier: Programming Language :: Python :: 3
Classifier: License :: OSI Approved :: MIT License
Classifier: Development Status :: 3 - Alpha
Classifier: Environment :: Console
Classifier: Operating System :: Microsoft :: Windows
Classifier: Programming Language :: Python :: 3.8
Requires-Python: >=3.8
License-File: LICENSE
